flow_framework/__init__.py
flow_framework/flow/__init__.py
flow_framework/flow/constants.py
flow_framework/flow/exceptions.py
flow_framework/flow/flow_nodes.py
flow_framework-0.1.1.dist-info/METADATA
flow_framework-0.1.1.dist-info/WHEEL
flow_framework-0.1.1.dist-info/entry_points.txt
flow_framework-0.1.1.dist-info/licenses/LICENSE
flow_framework-0.1.1.dist-info/RECORD
